urllib3_odigos/__init__.py
urllib3_odigos/_base_connection.py
urllib3_odigos/_collections.py
urllib3_odigos/_request_methods.py
urllib3_odigos/_version.py
urllib3_odigos/connection.py
urllib3_odigos/connectionpool.py
urllib3_odigos/exceptions.py
urllib3_odigos/fields.py
urllib3_odigos/filepost.py
urllib3_odigos/http2.py
urllib3_odigos/poolmanager.py
urllib3_odigos/py.typed
urllib3_odigos/response.py
urllib3_odigos/contrib/__init__.py
urllib3_odigos/contrib/pyopenssl.py
urllib3_odigos/contrib/socks.py
urllib3_odigos/contrib/emscripten/__init__.py
urllib3_odigos/contrib/emscripten/connection.py
urllib3_odigos/contrib/emscripten/emscripten_fetch_worker.js
urllib3_odigos/contrib/emscripten/fetch.py
urllib3_odigos/contrib/emscripten/request.py
urllib3_odigos/contrib/emscripten/response.py
urllib3_odigos/util/__init__.py
urllib3_odigos/util/connection.py
urllib3_odigos/util/proxy.py
urllib3_odigos/util/request.py
urllib3_odigos/util/response.py
urllib3_odigos/util/retry.py
urllib3_odigos/util/ssl_.py
urllib3_odigos/util/ssl_match_hostname.py
urllib3_odigos/util/ssltransport.py
urllib3_odigos/util/timeout.py
urllib3_odigos/util/url.py
urllib3_odigos/util/util.py
urllib3_odigos/util/wait.py
urllib3_odigos-2.2.2.dist-info/METADATA
urllib3_odigos-2.2.2.dist-info/WHEEL
urllib3_odigos-2.2.2.dist-info/licenses/LICENSE.txt
urllib3_odigos-2.2.2.dist-info/RECORD
